setup.py
octoprint_remoteauth/__init__.py
octoprint_remoteauth.egg-info/PKG-INFO
octoprint_remoteauth.egg-info/SOURCES.txt
octoprint_remoteauth.egg-info/dependency_links.txt
octoprint_remoteauth.egg-info/not-zip-safe
octoprint_remoteauth.egg-info/top_level.txt