Metadata-Version: 1.0
Name: octoprint-remoteauth
Version: 0.1
Summary: Remote Login UserManager for OctoPrint
Home-page: https://github.com/bfritscher/octoprint_remoteauth
Author: Boris Fritscher
Author-email: boris.fritscher@gmail.com
License: GPLv3
Platform: UNKNOWN
